{
    "name": "ZKSwap Token List",
    "logoURI": "https://zks.org/logo/256.png",
    "version": {
        "major": 1,
        "minor": 0,
        "patch": 0
    },
    "keywords": ["ZKS", "ZKSwap"],
    "timestamp": "2021-01-05T04:43:29.077Z",
    "tokens": [
        {
            "name": "ZKS",
            "logoURI": "https://zks.org/logo/256.png",
            "address": "0xe4815ae53b124e7263f08dcdbbb757d41ed658c6",
            "chainId": 1,
            "symbol": "ZKS",
            "decimals": 18
        },
        {
            "name": "USDT",
            "logoURI": "https://raw.githubusercontent.com/trustwallet/assets/master/blockchains/ethereum/assets/0xdAC17F958D2ee523a2206206994597C13D831ec7/logo.png",
            "address": "0xdac17f958d2ee523a2206206994597c13d831ec7",
            "chainId": 1,
            "symbol": "USDT",
            "decimals": 6
        },
        {
            "name": "Robonomics Network",
            "logoURI": "https://raw.githubusercontent.com/trustwallet/assets/master/blockchains/ethereum/assets/0x7dE91B204C1C737bcEe6F000AAA6569Cf7061cb7/logo.png",
            "address": "0x7dE91B204C1C737bcEe6F000AAA6569Cf7061cb7",
            "chainId": 1,
            "symbol": "XRT",
            "decimals": 9
        }
    ]
}
